{
  "name": "wa-core-router",
  "nodes": [
    {
      "id": "WebhookIn",
      "name": "WA Webhook",
      "type": "n8n-nodes-base.webhook",
      "typeVersion": 1,
      "position": [
        200,
        320
      ],
      "parameters": {
        "path": "waha/incoming",
        "httpMethod": "POST"
      }
    },
    {
      "id": "PersistMessage",
      "name": "Persist Message",
      "type": "n8n-nodes-base.httpRequest",
      "typeVersion": 4.2,
      "position": [
        440,
        320
      ],
      "parameters": {
        "method": "POST",
        "url": "http://backend:4000/api/webhook/waha",
        "sendBody": true,
        "specifyBody": "json",
        "jsonBody": "={\n  \"waNumber\": $json.body?.waNumber || $json.waNumber || $json.from || '',\n  \"body\": $json.body?.body || $json.body || $json.text || '',\n  \"messageId\": $json.body?.messageId || $json.messageId || $json.id || '',\n  \"timestamp\": $json.body?.timestamp || $json.timestamp || $now.toISO()\n}"
      }
    },
    {
      "id": "Precheck",
      "name": "Precheck Thread",
      "type": "n8n-nodes-base.httpRequest",
      "typeVersion": 4.2,
      "position": [
        680,
        320
      ],
      "parameters": {
        "method": "POST",
        "url": "http://backend:4000/api/chat/precheck",
        "sendBody": true,
        "bodyParametersUi": {
          "parameter": [
            {
              "name": "waNumber",
              "value": "={{$node[\"WA Webhook\"].json.body?.waNumber || $node[\"WA Webhook\"].json.waNumber || $node[\"WA Webhook\"].json.from || \"\"}}"
            }
          ]
        }
      }
    },
    {
      "id": "IfAllowed",
      "name": "Allowed?",
      "type": "n8n-nodes-base.if",
      "typeVersion": 2,
      "position": [
        920,
        320
      ],
      "parameters": {
        "conditions": {
          "boolean": [
            {
              "value1": "={{$json[\"allowed\"]}}",
              "operation": "isTrue"
            }
          ]
        }
      }
    },
    {
      "id": "Classify",
      "name": "Classify Intent",
      "type": "n8n-nodes-base.httpRequest",
      "typeVersion": 4.2,
      "position": [
        1160,
        320
      ],
      "parameters": {
        "method": "POST",
        "url": "http://backend:4000/api/chat/classify",
        "sendBody": true,
        "specifyBody": "json",
        "jsonBody": "={\n  \"threadId\": $node[\"Persist Message\"].json.threadId || '',\n  \"text\": $node[\"WA Webhook\"].json.body?.body || $node[\"WA Webhook\"].json.body || $node[\"WA Webhook\"].json.text || '',\n  \"metadata\": {\n    \"waNumber\": $node[\"WA Webhook\"].json.body?.waNumber || $node[\"WA Webhook\"].json.waNumber || $node[\"WA Webhook\"].json.from || '',\n    \"broadcastCode\": $node[\"WA Webhook\"].json.body?.broadcastCode || $node[\"WA Webhook\"].json.broadcastCode || ''\n  }\n}"
      }
    },
    {
      "id": "RouteBySubflow",
      "name": "Route Subflow",
      "type": "n8n-nodes-base.switch",
      "typeVersion": 3,
      "position": [
        1400,
        320
      ],
      "parameters": {
        "propertyName": "={{$json[\"subflow\"]}}",
        "rules": [
          {
            "operation": "equal",
            "value": "A"
          },
          {
            "operation": "equal",
            "value": "B"
          },
          {
            "operation": "equal",
            "value": "C"
          },
          {
            "operation": "equal",
            "value": "D"
          },
          {
            "operation": "equal",
            "value": "E"
          },
          {
            "operation": "equal",
            "value": "F"
          },
          {
            "operation": "equal",
            "value": "G"
          },
          {
            "operation": "equal",
            "value": "H"
          },
          {
            "operation": "equal",
            "value": "I"
          }
        ]
      }
    },
    {
      "id": "EscalateFallback",
      "name": "Escalate Fallback",
      "type": "n8n-nodes-base.httpRequest",
      "typeVersion": 4.2,
      "position": [
        1640,
        440
      ],
      "parameters": {
        "method": "POST",
        "url": "http://backend:4000/api/handover/escalate",
        "sendBody": true,
        "specifyBody": "json",
        "jsonBody": "={\n  \"threadId\": $node[\"Persist Message\"].json.threadId || '',\n  \"type\": \"fallback\",\n  \"targetRole\": \"cs\",\n  \"reason\": `Auto fallback from intent classifier: ${$json.intent || 'unknown'}`\n}"
      }
    },
    {
      "id": "ValidateBookingA",
      "name": "Validate Booking (A)",
      "type": "n8n-nodes-base.httpRequest",
      "typeVersion": 4.2,
      "position": [
        1640,
        140
      ],
      "parameters": {
        "method": "POST",
        "url": "http://backend:4000/api/booking/validate",
        "sendBody": true,
        "specifyBody": "json",
        "jsonBody": "={\n  \"scheduleAt\": $node[\"WA Webhook\"].json.body?.scheduleAt || $node[\"WA Webhook\"].json.scheduleAt || $now.plus({ days: 1 }).set({ hour: 10, minute: 0, second: 0, millisecond: 0 }).toISO(),\n  \"branchCloseHour\": \"17:00\",\n  \"weekendCloseHour\": \"16:00\"\n}"
      }
    },
    {
      "id": "BookingWindowOK",
      "name": "Booking Window OK?",
      "type": "n8n-nodes-base.if",
      "typeVersion": 2,
      "position": [
        1880,
        140
      ],
      "parameters": {
        "conditions": {
          "boolean": [
            {
              "value1": "={{$json[\"valid\"]}}",
              "operation": "isTrue"
            }
          ]
        }
      }
    },
    {
      "id": "CreateBookingA",
      "name": "Create Booking (A)",
      "type": "n8n-nodes-base.httpRequest",
      "typeVersion": 4.2,
      "position": [
        2120,
        100
      ],
      "parameters": {
        "method": "POST",
        "url": "http://backend:4000/api/booking/create",
        "sendBody": true,
        "specifyBody": "json",
        "jsonBody": "={\n  \"threadId\": $node[\"Persist Message\"].json.threadId,\n  \"vehicle\": $node[\"WA Webhook\"].json.body?.vehicle || \"Honda Vario 125\",\n  \"plate\": $node[\"WA Webhook\"].json.body?.plate || \"B1234XYZ\",\n  \"serviceType\": $node[\"WA Webhook\"].json.body?.serviceType || \"servis berkala\",\n  \"scheduleAt\": $node[\"WA Webhook\"].json.body?.scheduleAt || $node[\"WA Webhook\"].json.scheduleAt || $now.plus({ days: 1 }).set({ hour: 10, minute: 0, second: 0, millisecond: 0 }).toISO(),\n  \"pickupFlag\": false\n}"
      }
    },
    {
      "id": "ReplyFallbackH",
      "name": "Reply Fallback (H)",
      "type": "n8n-nodes-base.httpRequest",
      "typeVersion": 4.2,
      "position": [
        1880,
        440
      ],
      "parameters": {
        "method": "POST",
        "url": "http://backend:4000/api/waha/send-text",
        "sendBody": true,
        "specifyBody": "json",
        "jsonBody": "={\n  \"session\": \"default\",\n  \"chatId\": $node[\"WA Webhook\"].json.body?.waNumber || $node[\"WA Webhook\"].json.waNumber || $node[\"WA Webhook\"].json.from || \"\",\n  \"text\": \"Halo, pesan kamu sudah kami teruskan ke admin kami ya. Mohon tunggu sebentar 🙏\"\n}"
      }
    },
    {
      "id": "ReplyBookingCreatedA",
      "name": "Reply Booking Created (A)",
      "type": "n8n-nodes-base.httpRequest",
      "typeVersion": 4.2,
      "position": [
        2360,
        100
      ],
      "parameters": {
        "method": "POST",
        "url": "http://backend:4000/api/waha/send-text",
        "sendBody": true,
        "specifyBody": "json",
        "jsonBody": "={\n  \"session\": \"default\",\n  \"chatId\": $node[\"WA Webhook\"].json.body?.waNumber || $node[\"WA Webhook\"].json.waNumber || $node[\"WA Webhook\"].json.from || \"\",\n  \"text\": `Booking berhasil dibuat. ID booking kamu: ${$json.bookingId}. Tim kami akan konfirmasi segera.`\n}"
      }
    },
    {
      "id": "ReplyBookingInvalidA",
      "name": "Reply Booking Invalid (A)",
      "type": "n8n-nodes-base.httpRequest",
      "typeVersion": 4.2,
      "position": [
        2120,
        180
      ],
      "parameters": {
        "method": "POST",
        "url": "http://backend:4000/api/waha/send-text",
        "sendBody": true,
        "specifyBody": "json",
        "jsonBody": "={\n  \"session\": \"default\",\n  \"chatId\": $node[\"WA Webhook\"].json.body?.waNumber || $node[\"WA Webhook\"].json.waNumber || $node[\"WA Webhook\"].json.from || \"\",\n  \"text\": \"Jadwal booking yang dipilih terlalu mepet jam tutup. Coba pilih jadwal lain ya 🙏\"\n}"
      }
    },
    {
      "id": "ValidatePickupB",
      "name": "Validate Pickup (B)",
      "type": "n8n-nodes-base.httpRequest",
      "typeVersion": 4.2,
      "position": [
        1640,
        280
      ],
      "parameters": {
        "method": "POST",
        "url": "http://backend:4000/api/pickup/validate",
        "sendBody": true,
        "specifyBody": "json",
        "jsonBody": "={\n  \"distanceKm\": Number($node[\"WA Webhook\"].json.body?.distanceKm || 1.5)\n}"
      }
    },
    {
      "id": "PickupInRangeB",
      "name": "Pickup In Range? (B)",
      "type": "n8n-nodes-base.if",
      "typeVersion": 2,
      "position": [
        1880,
        280
      ],
      "parameters": {
        "conditions": {
          "boolean": [
            {
              "value1": "={{$json[\"inRange\"]}}",
              "operation": "isTrue"
            }
          ]
        }
      }
    },
    {
      "id": "PickupNeedHumanB",
      "name": "Pickup Need Human? (B)",
      "type": "n8n-nodes-base.if",
      "typeVersion": 2,
      "position": [
        2120,
        260
      ],
      "parameters": {
        "conditions": {
          "boolean": [
            {
              "value1": "={{$json[\"requireHumanValidation\"]}}",
              "operation": "isTrue"
            }
          ]
        }
      }
    },
    {
      "id": "CreatePickupAutoB",
      "name": "Create Pickup Auto (B)",
      "type": "n8n-nodes-base.httpRequest",
      "typeVersion": 4.2,
      "position": [
        2360,
        220
      ],
      "parameters": {
        "method": "POST",
        "url": "http://backend:4000/api/pickup/create",
        "sendBody": true,
        "specifyBody": "json",
        "jsonBody": "={\n  \"threadId\": $node[\"Persist Message\"].json.threadId,\n  \"distanceKm\": Number($node[\"Validate Pickup (B)\"].json.distanceKm || 1.5),\n  \"estCost\": Number($node[\"Validate Pickup (B)\"].json.estCost || 0),\n  \"requireHumanValidation\": false,\n  \"status\": \"approved\"\n}"
      }
    },
    {
      "id": "ReplyPickupAutoB",
      "name": "Reply Pickup Auto (B)",
      "type": "n8n-nodes-base.httpRequest",
      "typeVersion": 4.2,
      "position": [
        2600,
        220
      ],
      "parameters": {
        "method": "POST",
        "url": "http://backend:4000/api/waha/send-text",
        "sendBody": true,
        "specifyBody": "json",
        "jsonBody": "={\n  \"session\": \"default\",\n  \"chatId\": $node[\"WA Webhook\"].json.body?.chatId || $node[\"WA Webhook\"].json.body?.waNumber || $node[\"WA Webhook\"].json.waNumber || $node[\"WA Webhook\"].json.from || \"\",\n  \"text\": \"Pickup berhasil dikonfirmasi. Tim kami akan lanjut proses penjemputan sesuai jadwal.\"\n}"
      }
    },
    {
      "id": "EscalatePickupB",
      "name": "Escalate Pickup Validation (B)",
      "type": "n8n-nodes-base.httpRequest",
      "typeVersion": 4.2,
      "position": [
        2360,
        300
      ],
      "parameters": {
        "method": "POST",
        "url": "http://backend:4000/api/handover/escalate",
        "sendBody": true,
        "specifyBody": "json",
        "jsonBody": "={\n  \"threadId\": $node[\"Persist Message\"].json.threadId,\n  \"type\": \"pickup_validation\",\n  \"targetRole\": \"cs\",\n  \"reason\": \"Pickup >2km membutuhkan validasi human\"\n}"
      }
    },
    {
      "id": "ReplyPickupPendingB",
      "name": "Reply Pickup Pending (B)",
      "type": "n8n-nodes-base.httpRequest",
      "typeVersion": 4.2,
      "position": [
        2600,
        300
      ],
      "parameters": {
        "method": "POST",
        "url": "http://backend:4000/api/waha/send-text",
        "sendBody": true,
        "specifyBody": "json",
        "jsonBody": "={\n  \"session\": \"default\",\n  \"chatId\": $node[\"WA Webhook\"].json.body?.chatId || $node[\"WA Webhook\"].json.body?.waNumber || $node[\"WA Webhook\"].json.waNumber || $node[\"WA Webhook\"].json.from || \"\",\n  \"text\": \"Pickup kamu kami terima, tapi perlu validasi admin dulu karena jarak di atas 2 km. Tim kami segera hubungi ya.\"\n}"
      }
    },
    {
      "id": "ReplyPickupOutRangeB",
      "name": "Reply Pickup Out of Range (B)",
      "type": "n8n-nodes-base.httpRequest",
      "typeVersion": 4.2,
      "position": [
        2120,
        340
      ],
      "parameters": {
        "method": "POST",
        "url": "http://backend:4000/api/waha/send-text",
        "sendBody": true,
        "specifyBody": "json",
        "jsonBody": "={\n  \"session\": \"default\",\n  \"chatId\": $node[\"WA Webhook\"].json.body?.chatId || $node[\"WA Webhook\"].json.body?.waNumber || $node[\"WA Webhook\"].json.waNumber || $node[\"WA Webhook\"].json.from || \"\",\n  \"text\": \"Maaf, layanan pickup saat ini maksimal 7 km dari bengkel. Kami bisa bantu booking datang langsung ya.\"\n}"
      }
    },
    {
      "id": "KnowledgeReplyC",
      "name": "Knowledge Reply (C)",
      "type": "n8n-nodes-base.httpRequest",
      "typeVersion": 4.2,
      "position": [
        1640,
        -120
      ],
      "parameters": {
        "method": "POST",
        "url": "http://backend:4000/api/knowledge/reply",
        "sendBody": true,
        "specifyBody": "json",
        "jsonBody": "={\n  \"text\": $node[\"WA Webhook\"].json.body?.body || $node[\"WA Webhook\"].json.body || \"\"\n}"
      }
    },
    {
      "id": "ReplyFaqC",
      "name": "Reply FAQ (C)",
      "type": "n8n-nodes-base.httpRequest",
      "typeVersion": 4.2,
      "position": [
        1880,
        -120
      ],
      "parameters": {
        "method": "POST",
        "url": "http://backend:4000/api/waha/send-text",
        "sendBody": true,
        "specifyBody": "json",
        "jsonBody": "={\n  \"session\": \"default\",\n  \"chatId\": $node[\"WA Webhook\"].json.body?.chatId || $node[\"WA Webhook\"].json.body?.waNumber || $node[\"WA Webhook\"].json.waNumber || $node[\"WA Webhook\"].json.from || \"\",\n  \"text\": $json.reply || \"Jam operasional kami weekday 08:00-17:00 dan weekend 08:00-16:00 ya.\"\n}"
      }
    },
    {
      "id": "GetHistoryD",
      "name": "Get History (D)",
      "type": "n8n-nodes-base.httpRequest",
      "typeVersion": 4.2,
      "position": [
        1640,
        0
      ],
      "parameters": {
        "method": "GET",
        "url": "={{\"http://backend:4000/api/history/\" + encodeURIComponent((($node[\"WA Webhook\"].json.body?.body || \"\").match(/[A-Za-z]{1,2}\\s?\\d{1,4}\\s?[A-Za-z]{0,3}/)?.[0] || \"B1234XYZ\").replace(/\\s+/g, \"\"))}}"
      }
    },
    {
      "id": "HistoryFoundD",
      "name": "History Found? (D)",
      "type": "n8n-nodes-base.if",
      "typeVersion": 2,
      "position": [
        1880,
        0
      ],
      "parameters": {
        "conditions": {
          "boolean": [
            {
              "value1": "={{!!$json.history}}",
              "operation": "isTrue"
            }
          ]
        }
      }
    },
    {
      "id": "ReplyHistoryFoundD",
      "name": "Reply History Found (D)",
      "type": "n8n-nodes-base.httpRequest",
      "typeVersion": 4.2,
      "position": [
        2120,
        -40
      ],
      "parameters": {
        "method": "POST",
        "url": "http://backend:4000/api/waha/send-text",
        "sendBody": true,
        "specifyBody": "json",
        "jsonBody": "={\n  \"session\": \"default\",\n  \"chatId\": $node[\"WA Webhook\"].json.body?.chatId || $node[\"WA Webhook\"].json.body?.waNumber || $node[\"WA Webhook\"].json.waNumber || $node[\"WA Webhook\"].json.from || \"\",\n  \"text\": \"Riwayat servis ditemukan. Servis terakhir: \" + ($json.history?.last_service_at || \"-\") + \". Catatan: \" + ($json.history?.notes || \"tidak ada\")\n}"
      }
    },
    {
      "id": "ReplyHistoryNotFoundD",
      "name": "Reply History Not Found (D)",
      "type": "n8n-nodes-base.httpRequest",
      "typeVersion": 4.2,
      "position": [
        2120,
        40
      ],
      "parameters": {
        "method": "POST",
        "url": "http://backend:4000/api/waha/send-text",
        "sendBody": true,
        "specifyBody": "json",
        "jsonBody": "={\n  \"session\": \"default\",\n  \"chatId\": $node[\"WA Webhook\"].json.body?.chatId || $node[\"WA Webhook\"].json.body?.waNumber || $node[\"WA Webhook\"].json.waNumber || $node[\"WA Webhook\"].json.from || \"\",\n  \"text\": \"Maaf, riwayat servis belum ditemukan untuk nopol itu. Bisa kirim ulang format nopolnya ya.\"\n}"
      }
    },
    {
      "id": "KnowledgeReplyE",
      "name": "Knowledge Reply (E)",
      "type": "n8n-nodes-base.httpRequest",
      "typeVersion": 4.2,
      "position": [
        1640,
        580
      ],
      "parameters": {
        "method": "POST",
        "url": "http://backend:4000/api/knowledge/reply",
        "sendBody": true,
        "specifyBody": "json",
        "jsonBody": "={\n  \"text\": $node[\"WA Webhook\"].json.body?.body || $node[\"WA Webhook\"].json.body || \"\"\n}"
      }
    },
    {
      "id": "ReplyConsultationE",
      "name": "Reply Consultation (E)",
      "type": "n8n-nodes-base.httpRequest",
      "typeVersion": 4.2,
      "position": [
        1880,
        580
      ],
      "parameters": {
        "method": "POST",
        "url": "http://backend:4000/api/waha/send-text",
        "sendBody": true,
        "specifyBody": "json",
        "jsonBody": "={\n  \"session\": \"default\",\n  \"chatId\": $node[\"WA Webhook\"].json.body?.chatId || $node[\"WA Webhook\"].json.body?.waNumber || $node[\"WA Webhook\"].json.waNumber || $node[\"WA Webhook\"].json.from || \"\",\n  \"text\": $json.reply || \"Bisa dijelaskan gejala motornya? Nanti kami bantu rekomendasi awal ya.\"\n}"
      }
    },
    {
      "id": "ResolveBranchF",
      "name": "Resolve Branch (F)",
      "type": "n8n-nodes-base.httpRequest",
      "typeVersion": 4.2,
      "position": [
        1640,
        720
      ],
      "parameters": {
        "method": "POST",
        "url": "http://backend:4000/api/routing/resolve-branch",
        "sendBody": true,
        "specifyBody": "json",
        "jsonBody": "={\n  \"sourceBranch\": $node[\"WA Webhook\"].json.body?.sourceBranch || null,\n  \"customerLat\": Number($node[\"WA Webhook\"].json.body?.customerLat || -6.2),\n  \"customerLng\": Number($node[\"WA Webhook\"].json.body?.customerLng || 106.8)\n}"
      }
    },
    {
      "id": "TransferAllowedF",
      "name": "Transfer Allowed? (F)",
      "type": "n8n-nodes-base.if",
      "typeVersion": 2,
      "position": [
        1880,
        720
      ],
      "parameters": {
        "conditions": {
          "boolean": [
            {
              "value1": "={{$json.transferAllowed}}",
              "operation": "isTrue"
            }
          ]
        }
      }
    },
    {
      "id": "ReplyRoutingSuccessF",
      "name": "Reply Routing Success (F)",
      "type": "n8n-nodes-base.httpRequest",
      "typeVersion": 4.2,
      "position": [
        2120,
        680
      ],
      "parameters": {
        "method": "POST",
        "url": "http://backend:4000/api/waha/send-text",
        "sendBody": true,
        "specifyBody": "json",
        "jsonBody": "={\n  \"session\": \"default\",\n  \"chatId\": $node[\"WA Webhook\"].json.body?.chatId || $node[\"WA Webhook\"].json.body?.waNumber || $node[\"WA Webhook\"].json.waNumber || $node[\"WA Webhook\"].json.from || \"\",\n  \"text\": \"Cabang terdekat untuk kamu: \" + ($json.targetBranch || \"-\") + \" (jarak \" + ($json.distanceKm || \"-\") + \" km).\"\n}"
      }
    },
    {
      "id": "ReplyRoutingFailF",
      "name": "Reply Routing Fail (F)",
      "type": "n8n-nodes-base.httpRequest",
      "typeVersion": 4.2,
      "position": [
        2120,
        760
      ],
      "parameters": {
        "method": "POST",
        "url": "http://backend:4000/api/waha/send-text",
        "sendBody": true,
        "specifyBody": "json",
        "jsonBody": "={\n  \"session\": \"default\",\n  \"chatId\": $node[\"WA Webhook\"].json.body?.chatId || $node[\"WA Webhook\"].json.body?.waNumber || $node[\"WA Webhook\"].json.waNumber || $node[\"WA Webhook\"].json.from || \"\",\n  \"text\": \"Lokasi kamu belum bisa diproses untuk routing cabang. Boleh kirim share location ya.\"\n}"
      }
    },
    {
      "id": "EscalateComplaintG",
      "name": "Escalate Complaint (G)",
      "type": "n8n-nodes-base.httpRequest",
      "typeVersion": 4.2,
      "position": [
        1640,
        860
      ],
      "parameters": {
        "method": "POST",
        "url": "http://backend:4000/api/handover/escalate",
        "sendBody": true,
        "specifyBody": "json",
        "jsonBody": "={\n  \"threadId\": $node[\"Persist Message\"].json.threadId || '',\n  \"type\": \"complaint\",\n  \"targetRole\": \"cs\",\n  \"reason\": \"Auto escalation for complaint intent\"\n}"
      }
    },
    {
      "id": "ReplyComplaintG",
      "name": "Reply Complaint (G)",
      "type": "n8n-nodes-base.httpRequest",
      "typeVersion": 4.2,
      "position": [
        1880,
        860
      ],
      "parameters": {
        "method": "POST",
        "url": "http://backend:4000/api/waha/send-text",
        "sendBody": true,
        "specifyBody": "json",
        "jsonBody": "={\n  \"session\": \"default\",\n  \"chatId\": $node[\"WA Webhook\"].json.body?.chatId || $node[\"WA Webhook\"].json.body?.waNumber || $node[\"WA Webhook\"].json.waNumber || $node[\"WA Webhook\"].json.from || \"\",\n  \"text\": \"Mohon maaf atas ketidaknyamanannya. Laporan kamu sudah kami eskalasi ke admin untuk ditindaklanjuti.\"\n}"
      }
    },
    {
      "id": "ReplyCampaignI",
      "name": "Reply Campaign (I)",
      "type": "n8n-nodes-base.httpRequest",
      "typeVersion": 4.2,
      "position": [
        1640,
        1000
      ],
      "parameters": {
        "method": "POST",
        "url": "http://backend:4000/api/waha/send-text",
        "sendBody": true,
        "specifyBody": "json",
        "jsonBody": "={\n  \"session\": \"default\",\n  \"chatId\": $node[\"WA Webhook\"].json.body?.chatId || $node[\"WA Webhook\"].json.body?.waNumber || $node[\"WA Webhook\"].json.waNumber || $node[\"WA Webhook\"].json.from || \"\",\n  \"text\": $node[\"WA Webhook\"].json.body?.broadcastCode === \"CXCT01\"\n    ? \"Promo CXCT01 aktif. Tim kami siap bantu proses booking/pickup kamu sekarang.\"\n    : $node[\"WA Webhook\"].json.body?.broadcastCode === \"CXCT02\"\n      ? \"Terima kasih follow-up CXCT02. Boleh kirim jadwal yang kamu inginkan?\"\n      : $node[\"WA Webhook\"].json.body?.broadcastCode === \"CXCT03\"\n        ? \"Kami terima pesan campaign CXCT03. Jika butuh bantuan admin, langsung ketik *admin* ya.\"\n        : \"Pesan campaign sudah kami terima. Tim kami akan follow-up segera.\"\n}"
      }
    },
    {
      "id": "CheckBlockReason",
      "name": "Check Block Reason",
      "type": "n8n-nodes-base.if",
      "typeVersion": 2,
      "position": [
        1120,
        460
      ],
      "parameters": {
        "conditions": {
          "string": [
            {
              "value1": "={{$json['reason']}}",
              "operation": "notContains",
              "value2": "non_ai"
            }
          ]
        }
      }
    },
    {
      "id": "SilentDropNonAi",
      "name": "Silent Drop (Non-AI)",
      "type": "n8n-nodes-base.noOp",
      "typeVersion": 1,
      "position": [
        1340,
        420
      ]
    },
    {
      "id": "GoogleSheetsAppend",
      "name": "Save to Google Sheet",
      "type": "n8n-nodes-base.set",
      "typeVersion": 3,
      "position": [
        2440,
        20
      ],
      "parameters": {
        "mode": "manual",
        "assignments": {
          "assignments": [
            {
              "id": "booking_msg",
              "name": "booking_msg",
              "type": "string",
              "value": "={{\"[Booking] ID: \" + ($json.bookingId || \"-\") + \" | WA: \" + ($node[\\\"WA Webhook\\\"].json.waNumber || \"-\") + \" | Vehicle: \" + ($json.vehicle || \"-\") + \" | Plate: \" + ($json.plate || \"-\") + \" | Schedule: \" + ($json.scheduleAt || \"-\") + \" | Pickup: \" + ($json.pickupFlag ? \"Ya\" : \"Tidak\")}}"
            }
          ]
        }
      }
    }
  ],
  "connections": {
    "WA Webhook": {
      "main": [
        [
          {
            "node": "Persist Message",
            "type": "main",
            "index": 0
          }
        ]
      ]
    },
    "Persist Message": {
      "main": [
        [
          {
            "node": "Precheck Thread",
            "type": "main",
            "index": 0
          }
        ]
      ]
    },
    "Precheck Thread": {
      "main": [
        [
          {
            "node": "Allowed?",
            "type": "main",
            "index": 0
          }
        ]
      ]
    },
    "Allowed?": {
      "main": [
        [
          {
            "node": "Classify Intent",
            "type": "main",
            "index": 0
          }
        ],
        [
          {
            "node": "Check Block Reason",
            "type": "main",
            "index": 0
          }
        ]
      ]
    },
    "Check Block Reason": {
      "main": [
        [
          {
            "node": "Silent Drop (Non-AI)",
            "type": "main",
            "index": 0
          }
        ],
        [
          {
            "node": "Escalate Fallback",
            "type": "main",
            "index": 0
          }
        ]
      ]
    },
    "Classify Intent": {
      "main": [
        [
          {
            "node": "Route Subflow",
            "type": "main",
            "index": 0
          }
        ]
      ]
    },
    "Route Subflow": {
      "main": [
        [
          {
            "node": "Validate Booking (A)",
            "type": "main",
            "index": 0
          }
        ],
        [
          {
            "node": "Validate Pickup (B)",
            "type": "main",
            "index": 0
          }
        ],
        [
          {
            "node": "Knowledge Reply (C)",
            "type": "main",
            "index": 0
          }
        ],
        [
          {
            "node": "Get History (D)",
            "type": "main",
            "index": 0
          }
        ],
        [
          {
            "node": "Knowledge Reply (E)",
            "type": "main",
            "index": 0
          }
        ],
        [
          {
            "node": "Resolve Branch (F)",
            "type": "main",
            "index": 0
          }
        ],
        [
          {
            "node": "Escalate Complaint (G)",
            "type": "main",
            "index": 0
          }
        ],
        [
          {
            "node": "Escalate Fallback",
            "type": "main",
            "index": 0
          }
        ],
        [
          {
            "node": "Reply Campaign (I)",
            "type": "main",
            "index": 0
          }
        ]
      ]
    },
    "Validate Booking (A)": {
      "main": [
        [
          {
            "node": "Booking Window OK?",
            "type": "main",
            "index": 0
          }
        ]
      ]
    },
    "Booking Window OK?": {
      "main": [
        [
          {
            "node": "Create Booking (A)",
            "type": "main",
            "index": 0
          }
        ],
        [
          {
            "node": "Reply Booking Invalid (A)",
            "type": "main",
            "index": 0
          }
        ]
      ]
    },
    "Create Booking (A)": {
      "main": [
        [
          {
            "node": "Reply Booking Created (A)",
            "type": "main",
            "index": 0
          }
        ]
      ]
    },
    "Reply Booking Created (A)": {
      "main": [
        [
          {
            "node": "Save to Google Sheet",
            "type": "main",
            "index": 0
          }
        ]
      ]
    },
    "Escalate Fallback": {
      "main": [
        [
          {
            "node": "Reply Fallback (H)",
            "type": "main",
            "index": 0
          }
        ]
      ]
    },
    "Validate Pickup (B)": {
      "main": [
        [
          {
            "node": "Pickup In Range? (B)",
            "type": "main",
            "index": 0
          }
        ]
      ]
    },
    "Pickup In Range? (B)": {
      "main": [
        [
          {
            "node": "Pickup Need Human? (B)",
            "type": "main",
            "index": 0
          }
        ],
        [
          {
            "node": "Reply Pickup Out of Range (B)",
            "type": "main",
            "index": 0
          }
        ]
      ]
    },
    "Pickup Need Human? (B)": {
      "main": [
        [
          {
            "node": "Escalate Pickup Validation (B)",
            "type": "main",
            "index": 0
          }
        ],
        [
          {
            "node": "Create Pickup Auto (B)",
            "type": "main",
            "index": 0
          }
        ]
      ]
    },
    "Create Pickup Auto (B)": {
      "main": [
        [
          {
            "node": "Reply Pickup Auto (B)",
            "type": "main",
            "index": 0
          }
        ]
      ]
    },
    "Escalate Pickup Validation (B)": {
      "main": [
        [
          {
            "node": "Reply Pickup Pending (B)",
            "type": "main",
            "index": 0
          }
        ]
      ]
    },
    "Knowledge Reply (C)": {
      "main": [
        [
          {
            "node": "Reply FAQ (C)",
            "type": "main",
            "index": 0
          }
        ]
      ]
    },
    "Get History (D)": {
      "main": [
        [
          {
            "node": "History Found? (D)",
            "type": "main",
            "index": 0
          }
        ]
      ]
    },
    "History Found? (D)": {
      "main": [
        [
          {
            "node": "Reply History Found (D)",
            "type": "main",
            "index": 0
          }
        ],
        [
          {
            "node": "Reply History Not Found (D)",
            "type": "main",
            "index": 0
          }
        ]
      ]
    },
    "Knowledge Reply (E)": {
      "main": [
        [
          {
            "node": "Reply Consultation (E)",
            "type": "main",
            "index": 0
          }
        ]
      ]
    },
    "Resolve Branch (F)": {
      "main": [
        [
          {
            "node": "Transfer Allowed? (F)",
            "type": "main",
            "index": 0
          }
        ]
      ]
    },
    "Transfer Allowed? (F)": {
      "main": [
        [
          {
            "node": "Reply Routing Success (F)",
            "type": "main",
            "index": 0
          }
        ],
        [
          {
            "node": "Reply Routing Fail (F)",
            "type": "main",
            "index": 0
          }
        ]
      ]
    },
    "Escalate Complaint (G)": {
      "main": [
        [
          {
            "node": "Reply Complaint (G)",
            "type": "main",
            "index": 0
          }
        ]
      ]
    }
  }
}
